{
  "_class": "group",
  "do_objectID": "9D032265-9DF5-4604-B7E2-949C57DE174A",
  "exportOptions": {
    "_class": "exportOptions",
    "exportFormats": [
    ],
    "includedLayerIds": [
    ],
    "layerOptions": 0,
    "shouldTrim": false
  },
  "frame": {
    "_class": "rect",
    "constrainProportions": false,
    "height": 24,
    "width": 288,
    "x": 624,
    "y": 8
  },
  "hasClickThrough": false,
  "isFlippedHorizontal": false,
  "isFlippedVertical": false,
  "isLocked": false,
  "isVisible": true,
  "layerListExpandedType": 0,
  "layers": [
    {
      "class": "shapeGroup",
      "id": "D3A0CA4E-7571-422C-88B6-4795FE95F492"
    },
    {
      "class": "text",
      "id": "CDEEF17B-862E-4226-A58F-1D9D84CBD00B"
    },
    {
      "class": "text",
      "id": "BBA13892-A65F-4FC5-AEA6-6C321A483A58"
    },
    {
      "class": "text",
      "id": "2AE05C12-03EF-4B7D-809A-E18E433416CC"
    },
    {
      "class": "text",
      "id": "FDC37CEC-CB63-4403-B844-4690B808FB86"
    },
    {
      "class": "text",
      "id": "518EFC46-5A25-4F8A-B9DD-4693E5D84A4D"
    },
    {
      "class": "text",
      "id": "A12B51A6-3427-4EDB-9E4F-D85715916C7C"
    },
    {
      "class": "text",
      "id": "E8157FDD-82BA-49E9-BC8B-A1DD10BB61E4"
    },
    {
      "class": "text",
      "id": "111BB9D4-9D96-445A-9DEB-288A0C8B7089"
    },
    {
      "class": "symbolInstance",
      "id": "03AD4028-61D6-4432-8085-EA882D55086C"
    },
    {
      "class": "symbolInstance",
      "id": "22F2625F-2180-4F44-963D-8E1C25708C4B"
    },
    {
      "class": "symbolInstance",
      "id": "D4415EB8-CC60-4BB9-8AF4-8C495AC3B2A3"
    },
    {
      "class": "symbolInstance",
      "id": "448825AB-367D-4A47-84B5-4B9DF09B906D"
    }
  ],
  "name": "Pagination",
  "nameIsFixed": true,
  "resizingConstraint": 63,
  "resizingType": 0,
  "rotation": 0,
  "shouldBreakMaskChain": false,
  "style": {
    "_class": "style",
    "endDecorationType": 0,
    "miterLimit": 10,
    "startDecorationType": 0
  }
}