{
  "_class": "group",
  "do_objectID": "7CE39DC5-C336-41AF-A137-5308BF21F495",
  "exportOptions": {
    "_class": "exportOptions",
    "exportFormats": [
    ],
    "includedLayerIds": [
    ],
    "layerOptions": 0,
    "shouldTrim": false
  },
  "frame": {
    "_class": "rect",
    "constrainProportions": false,
    "height": 100,
    "width": 820,
    "x": 0,
    "y": 2303
  },
  "hasClickThrough": false,
  "isFlippedHorizontal": false,
  "isFlippedVertical": false,
  "isLocked": false,
  "isVisible": true,
  "layerListExpandedType": 0,
  "layers": [
    {
      "class": "shapeGroup",
      "id": "639115DE-1103-4058-8AED-82558512218C"
    },
    {
      "class": "text",
      "id": "4D6CCB48-B36B-4A45-AC63-23528F82E32B"
    },
    {
      "class": "text",
      "id": "89F50DA2-517A-47A2-8C77-BE63BE2CCB0A"
    },
    {
      "class": "text",
      "id": "B28AABA2-FC67-43E6-86E1-3440D135F2CC"
    }
  ],
  "name": "Text Style: 18",
  "nameIsFixed": false,
  "resizingConstraint": 63,
  "resizingType": 0,
  "rotation": 0,
  "shouldBreakMaskChain": false,
  "style": {
    "_class": "style",
    "endDecorationType": 0,
    "miterLimit": 10,
    "startDecorationType": 0
  }
}