{
  "_class": "group",
  "do_objectID": "6047E336-553C-41A2-94CD-8A6FD6B86CFF",
  "exportOptions": {
    "_class": "exportOptions",
    "exportFormats": [
    ],
    "includedLayerIds": [
    ],
    "layerOptions": 0,
    "shouldTrim": false
  },
  "frame": {
    "_class": "rect",
    "constrainProportions": false,
    "height": 36,
    "width": 88,
    "x": 8,
    "y": 156
  },
  "hasClickThrough": false,
  "isFlippedHorizontal": false,
  "isFlippedVertical": false,
  "isLocked": false,
  "isVisible": true,
  "layerListExpandedType": 0,
  "layers": [
    {
      "class": "shapeGroup",
      "id": "2C028A5F-759F-4300-A6DD-05C52F7ACF8B"
    },
    {
      "class": "text",
      "id": "33D1D9CD-2946-4F0B-A58F-30C39A4BA627"
    }
  ],
  "name": "button",
  "nameIsFixed": true,
  "resizingConstraint": 63,
  "resizingType": 0,
  "rotation": 0,
  "shouldBreakMaskChain": false,
  "style": {
    "_class": "style",
    "endDecorationType": 0,
    "miterLimit": 10,
    "startDecorationType": 0
  }
}