{
  "_class": "group",
  "do_objectID": "E4D14197-B5B9-41A3-B21B-FFD3B524933C",
  "exportOptions": {
    "_class": "exportOptions",
    "exportFormats": [
    ],
    "includedLayerIds": [
    ],
    "layerOptions": 0,
    "shouldTrim": false
  },
  "frame": {
    "_class": "rect",
    "constrainProportions": false,
    "height": 120,
    "width": 180,
    "x": 20,
    "y": 20
  },
  "hasClickThrough": false,
  "isFlippedHorizontal": false,
  "isFlippedVertical": false,
  "isLocked": false,
  "isVisible": true,
  "layerListExpandedType": 0,
  "layers": [
    {
      "class": "shapeGroup",
      "id": "01DFA20E-61A9-4712-A7A5-354FAF324E5C"
    },
    {
      "class": "text",
      "id": "91D2B8DE-46C1-4D5F-9DA7-EA10224B8582"
    },
    {
      "class": "text",
      "id": "E1DA59D2-79EC-4C9F-8531-755BF9741453"
    }
  ],
  "name": "Font: Montserrat-Regular",
  "nameIsFixed": false,
  "resizingConstraint": 63,
  "resizingType": 0,
  "rotation": 0,
  "shouldBreakMaskChain": false,
  "style": {
    "_class": "style",
    "endDecorationType": 0,
    "miterLimit": 10,
    "startDecorationType": 0
  }
}