{
  "_class": "shapeGroup",
  "clippingMaskMode": 0,
  "do_objectID": "FE0F85E5-0F1F-4E5E-8454-D5A51BC52326",
  "exportOptions": {
    "_class": "exportOptions",
    "exportFormats": [
    ],
    "includedLayerIds": [
    ],
    "layerOptions": 0,
    "shouldTrim": false
  },
  "frame": {
    "_class": "rect",
    "constrainProportions": false,
    "height": 56.00000000000001,
    "width": 328.0000000000001,
    "x": 0,
    "y": 143
  },
  "hasClickThrough": false,
  "hasClippingMask": false,
  "isFlippedHorizontal": false,
  "isFlippedVertical": false,
  "isLocked": false,
  "isVisible": true,
  "layerListExpandedType": 0,
  "layers": [
    {
      "class": "rectangle",
      "id": "0EDE53F0-EEBE-4A83-BF42-DF54D5A882F7"
    }
  ],
  "name": "Rectangle 7",
  "nameIsFixed": false,
  "resizingConstraint": 63,
  "resizingType": 0,
  "rotation": 0,
  "shouldBreakMaskChain": false,
  "style": {
    "sharedObjectID": "8D3E212E-7FDD-4B28-B882-732DB66A8F6C"
  },
  "windingRule": 1
}