{
  "_class": "symbolInstance",
  "do_objectID": "4C73CC25-7856-4C54-B639-3F7ECC3343DE",
  "exportOptions": {
    "_class": "exportOptions",
    "exportFormats": [
    ],
    "includedLayerIds": [
    ],
    "layerOptions": 0,
    "shouldTrim": false
  },
  "frame": {
    "_class": "rect",
    "constrainProportions": false,
    "height": 144,
    "width": 128,
    "x": 1296,
    "y": 16
  },
  "horizontalSpacing": 0,
  "isFlippedHorizontal": false,
  "isFlippedVertical": false,
  "isLocked": false,
  "isVisible": true,
  "layerListExpandedType": 0,
  "masterInfluenceEdgeMaxXPadding": 16,
  "masterInfluenceEdgeMaxYPadding": 24,
  "masterInfluenceEdgeMinXPadding": 16,
  "masterInfluenceEdgeMinYPadding": 8,
  "name": "Elements / Menus / #1",
  "nameIsFixed": false,
  "overrides": {
  },
  "resizingConstraint": 63,
  "resizingType": 0,
  "rotation": 0,
  "shouldBreakMaskChain": false,
  "style": {
    "_class": "style",
    "endDecorationType": 0,
    "miterLimit": 10,
    "startDecorationType": 0
  },
  "symbolID": "58DCD6DE-FDD1-4D63-88B7-728E300CAF72",
  "verticalSpacing": 0
}