{
  "_class": "group",
  "do_objectID": "68CFE35B-50F3-441A-AFB1-2C4ACE806BD2",
  "exportOptions": {
    "_class": "exportOptions",
    "exportFormats": [
    ],
    "includedLayerIds": [
    ],
    "layerOptions": 0,
    "shouldTrim": false
  },
  "frame": {
    "_class": "rect",
    "constrainProportions": false,
    "height": 100,
    "width": 820,
    "x": 0,
    "y": 2010
  },
  "hasClickThrough": false,
  "isFlippedHorizontal": false,
  "isFlippedVertical": false,
  "isLocked": false,
  "isVisible": true,
  "layerListExpandedType": 0,
  "layers": [
    {
      "class": "shapeGroup",
      "id": "0477DDCA-3FCB-4C33-B029-86CD4F67965C"
    },
    {
      "class": "text",
      "id": "E5E3F9F4-16C3-42A6-85B7-EFFF6D321AED"
    },
    {
      "class": "text",
      "id": "5557C680-A8A7-4D8E-8A8E-6259608DC4B7"
    },
    {
      "class": "text",
      "id": "BD74B800-4B32-4572-97A6-4A9A764B4688"
    }
  ],
  "name": "Text Style: 18",
  "nameIsFixed": false,
  "resizingConstraint": 63,
  "resizingType": 0,
  "rotation": 0,
  "shouldBreakMaskChain": false,
  "style": {
    "_class": "style",
    "endDecorationType": 0,
    "miterLimit": 10,
    "startDecorationType": 0
  }
}