{
  "_class": "shapePath",
  "booleanOperation": -1,
  "do_objectID": "12BAA92A-48F3-4542-BDFC-0E1422F4AE0F",
  "edited": true,
  "exportOptions": {
    "_class": "exportOptions",
    "exportFormats": [
    ],
    "includedLayerIds": [
    ],
    "layerOptions": 0,
    "shouldTrim": false
  },
  "frame": {
    "_class": "rect",
    "constrainProportions": false,
    "height": 116.76,
    "width": 127.25,
    "x": 0,
    "y": 0
  },
  "isFlippedHorizontal": false,
  "isFlippedVertical": false,
  "isLocked": false,
  "isVisible": true,
  "layerListExpandedType": 0,
  "name": "Path",
  "nameIsFixed": false,
  "path": {
    "_class": "path",
    "isClosed": true,
    "pointRadiusBehaviour": 0,
    "points": [
      {
        "_class": "curvePoint",
        "cornerRadius": 0,
        "curveFrom": "{0.038821218074656168, 0.58838643371017474}",
        "curveMode": 4,
        "curveTo": "{0, 0.97773210003425826}",
        "hasCurveFrom": true,
        "hasCurveTo": false,
        "point": "{0, 0.97773210003425826}"
      },
      {
        "_class": "curvePoint",
        "cornerRadius": 0,
        "curveFrom": "{0.72204322200392923, 0.031774580335731363}",
        "curveMode": 3,
        "curveTo": "{0.26538310412573674, 0.25119904076738608}",
        "hasCurveFrom": true,
        "hasCurveTo": true,
        "point": "{0.59418467583497048, 0.093182596779719046}"
      },
      {
        "_class": "curvePoint",
        "cornerRadius": 0,
        "curveFrom": "{1, 0}",
        "curveMode": 4,
        "curveTo": "{0.86027504911591357, 0}",
        "hasCurveFrom": false,
        "hasCurveTo": true,
        "point": "{1, 0}"
      },
      {
        "_class": "curvePoint",
        "cornerRadius": 0,
        "curveFrom": "{0.70797642436149311, 0.20554984583761562}",
        "curveMode": 4,
        "curveTo": "{1, 0.20554984583761562}",
        "hasCurveFrom": true,
        "hasCurveTo": false,
        "point": "{1, 0.20554984583761562}"
      },
      {
        "_class": "curvePoint",
        "cornerRadius": 0,
        "curveFrom": "{0.23544204322200399, 0.75805070229530647}",
        "curveMode": 3,
        "curveTo": "{0.43819253438113953, 0.37529976019184647}",
        "hasCurveFrom": true,
        "hasCurveTo": true,
        "point": "{0.29218074656188608, 0.65090784515244948}"
      },
      {
        "_class": "curvePoint",
        "cornerRadius": 0,
        "curveFrom": "{0.1875049115913556, 1}",
        "curveMode": 4,
        "curveTo": "{0.19976424361493125, 0.87701267557382667}",
        "hasCurveFrom": false,
        "hasCurveTo": true,
        "point": "{0.1875049115913556, 1}"
      }
    ]
  },
  "resizingConstraint": 63,
  "resizingType": 0,
  "rotation": 0,
  "shouldBreakMaskChain": false
}