{
  "_class": "group",
  "do_objectID": "B22E21AA-09D1-438C-9295-A19EA6126DC0",
  "exportOptions": {
    "_class": "exportOptions",
    "exportFormats": [
    ],
    "includedLayerIds": [
    ],
    "layerOptions": 0,
    "shouldTrim": false
  },
  "frame": {
    "_class": "rect",
    "constrainProportions": false,
    "height": 232,
    "width": 20,
    "x": 576,
    "y": 0
  },
  "hasClickThrough": false,
  "isFlippedHorizontal": false,
  "isFlippedVertical": false,
  "isLocked": false,
  "isVisible": true,
  "layerListExpandedType": 0,
  "layers": [
    {
      "class": "shapeGroup",
      "id": "7050F43F-C105-46C2-B43B-8DDA229C7D3F"
    },
    {
      "class": "shapeGroup",
      "id": "E39DCFC9-CB97-4067-9DFE-A1EA1EACDC73"
    },
    {
      "class": "shapeGroup",
      "id": "DA4C8237-31C4-4BBC-BDEC-3B09C3DF502E"
    },
    {
      "class": "shapeGroup",
      "id": "F3AEA34F-BFF4-46D1-938A-87F73C3983D4"
    }
  ],
  "name": "Rects",
  "nameIsFixed": true,
  "resizingConstraint": 63,
  "resizingType": 0,
  "rotation": 0,
  "shouldBreakMaskChain": false,
  "style": {
    "_class": "style",
    "endDecorationType": 0,
    "miterLimit": 10,
    "startDecorationType": 0
  }
}